teddy_utils/__init__.py
teddy_utils/utils.py
teddy_utils-0.1.dist-info/License.txt
teddy_utils-0.1.dist-info/METADATA
teddy_utils-0.1.dist-info/WHEEL
teddy_utils-0.1.dist-info/top_level.txt
teddy_utils-0.1.dist-info/RECORD
