Metadata-Version: 2.1
Name: teddy-utils
Version: 0.1
Summary: Just for learning packages
Home-page: UNKNOWN
Author: Mannem Srinivas
Author-email: m.srinivas365@gmail.com
License: UNKNOWN
Platform: UNKNOWN
Requires-Dist: numpy
